iphone_backup_decrypt/__init__.py
iphone_backup_decrypt/google_iphone_dataprotection.py
iphone_backup_decrypt/iphone_backup.py
iphone_backup_decrypt/utils.py
iphone_backup_decrypt-0.9.0.dist-info/LICENSE.txt
iphone_backup_decrypt-0.9.0.dist-info/METADATA
iphone_backup_decrypt-0.9.0.dist-info/WHEEL
iphone_backup_decrypt-0.9.0.dist-info/top_level.txt
iphone_backup_decrypt-0.9.0.dist-info/RECORD
