Metadata-Version: 2.1
Name: iphone_backup_decrypt
Version: 0.9.0
Summary: Decrypt and extract files from an iOS13+ encrypted local backup.
Author: James Sharkey
Project-URL: Homepage, https://github.com/jsharkey13/iphone_backup_decrypt
Keywords: iPhone,backup,forensics,iOS,WhatsApp,decryption,iOS backup,iTunes Backup
Classifier: Programming Language :: Python :: 3
Classifier: Topic :: Security :: Cryptography
Requires-Python: >=3.8
License-File: LICENSE.txt
Requires-Dist: pycryptodome >=3.20.0
Provides-Extra: fastpbkdf2
Requires-Dist: fastpbkdf2 >=0.2 ; extra == 'fastpbkdf2'
